flexitext/__init__.py
flexitext/flexitext.py
flexitext/style.py
flexitext/text.py
flexitext/textgrid.py
flexitext/utils.py
flexitext/parser/__init__.py
flexitext/parser/args.py
flexitext/parser/blocks.py
flexitext/parser/make_texts.py
flexitext/parser/utils.py
flexitext/parser/classes/__init__.py
flexitext/parser/classes/parser.py
flexitext/parser/classes/scanner.py
flexitext/parser/classes/token.py
flexitext/tests/__init__.py
flexitext/tests/test_flexitext.py
flexitext/tests/test_style.py
flexitext/tests/test_text.py
flexitext/tests/test_textgrid.py
flexitext/tests/test_utils.py
flexitext/tests/parser/test_args.py
flexitext/tests/parser/test_make_texts.py
flexitext/tests/parser/test_utils.py
flexitext-0.4.0.dist-info/LICENSE
flexitext-0.4.0.dist-info/METADATA
flexitext-0.4.0.dist-info/WHEEL
flexitext-0.4.0.dist-info/top_level.txt
flexitext-0.4.0.dist-info/RECORD
