Metadata-Version: 2.2
Name: flexitext
Version: 0.4.0
Summary: Draw styled text in Matplotlib
Maintainer-email: Tomás Capretto <tomicapretto@gmail.com>
License: Copyright 2019 Tomás Capretto and contributors
Project-URL: homepage, https://tomicapretto.com/flexitext
Project-URL: documentation, https://tomicapretto.com/flexitext
Project-URL: repository, https://github.com/tomicapretto/flexitext
Project-URL: changelog, https://github.com/tomicapretto/flexitext/blob/main/CHANGELOG.md
Classifier: Framework :: Matplotlib
Requires-Python: >=3.6
License-File: LICENSE
Requires-Dist: matplotlib>=3.4
Provides-Extra: dev
Requires-Dist: black==24.10.0; extra == "dev"
Requires-Dist: pylint==3.3.3; extra == "dev"
Requires-Dist: pytest-cov>=2.6.1; extra == "dev"
Requires-Dist: pytest>=4.4.0; extra == "dev"
